sphinxcontrib/soliditydomain/Solidity.g4
sphinxcontrib/soliditydomain/SolidityLexer.py
sphinxcontrib/soliditydomain/SolidityListener.py
sphinxcontrib/soliditydomain/SolidityParser.py
sphinxcontrib/soliditydomain/VERSION
sphinxcontrib/soliditydomain/__init__.py
sphinxcontrib/soliditydomain/documenters.py
sphinxcontrib/soliditydomain/domain.py
sphinxcontrib/soliditydomain/sourceregistry.py
sphinxcontrib_soliditydomain-0.5.1.dist-info/METADATA
sphinxcontrib_soliditydomain-0.5.1.dist-info/RECORD
sphinxcontrib_soliditydomain-0.5.1.dist-info/WHEEL
sphinxcontrib_soliditydomain-0.5.1.dist-info/top_level.txt
