Metadata-Version: 2.1
Name: sphinxcontrib-soliditydomain
Version: 0.5.1
Summary: Solidity domain for Sphinx
Home-page: https://github.com/cag/sphinxcontrib-soliditydomain
Author: Alan Lu
Author-email: alan@gnosis.pm
License: UNKNOWN
Keywords: sphinx solidity domain contrib documentation generator plugin
Platform: UNKNOWN
Classifier: Development Status :: 3 - Alpha
Classifier: Intended Audience :: Developers
Classifier: Topic :: Software Development :: Build Tools
Classifier: License :: OSI Approved :: MIT License
Classifier: Programming Language :: Python :: 3
Classifier: Programming Language :: Python :: 3.4
Classifier: Programming Language :: Python :: 3.5
Classifier: Programming Language :: Python :: 3.6
Requires-Dist: antlr4-python3-runtime
Requires-Dist: peewee
